phonegpt/__init__.py
phonegpt/phonegpt.py
phonegpt-1.9.2.dist-info/METADATA
phonegpt-1.9.2.dist-info/WHEEL
phonegpt-1.9.2.dist-info/top_level.txt
phonegpt-1.9.2.dist-info/RECORD
