Metadata-Version: 2.1
Name: phonegpt
Version: 1.9.2
Summary: Make interactive phone call, using Twilio and OpenAI
Home-page: https://github.com/ensood/phone-gpt
Author: Ehsan Amiri
Author-email: e.amiri89@gmail.com
License: UNKNOWN
Platform: UNKNOWN
Requires-Dist: openai
Requires-Dist: twilio
Requires-Dist: vosk
